{
    "title": "\u7279\u6b8a\u7684\u500d\u6570",
    "desc": "### \u9898\u76ee\u63cf\u8ff0\n\n\u4e00\u4e2a\u6570\u7684\u7279\u6b8a\u500d\u6570\u662f\u6307\u4ec5\u75311\u548c0\u6784\u6210\u7684\u500d\u6570\u3002\u598210\u662f2\u7684\u500d\u6570\uff0c\u540c\u65f6\u5b83\u53ea\u75311\u548c0\u6784\u6210\uff0c\u56e0\u6b64\u5b83\u662f2\u7684\u7279\u6b8a\u500d\u6570\u3002\n\n### \u8f93\u5165\u63cf\u8ff0\n\n\u8f93\u5165\u4e3a\u4e00\u4e2a\u6b63\u6574\u6570 n (0 < n < 10^3)\n\n### \u8f93\u51fa\u63cf\u8ff0\n\n\u8f93\u51fa\u4e3a n \u7684\u6700\u5c0f\u7279\u6b8a\u500d\u6570 m\uff0c\u6211\u4eec\u4fdd\u8bc1 m \u4e0d\u8d85\u8fc7\u6574\u6570\u8303\u56f4\n\n### \u6837\u4f8b\u8f93\u5165\n\n```\n2\n```\n\n```\n3\n```\n\n### \u6837\u4f8b\u8f93\u51fa\n\n```\n10\n```\n\n```\n111\n```\n",
    "templateCode": "",
    "sourceCode": "n = int(input())\n\ni=0\nwhile True:\n    i=i+1\n    if int(str(bin(i))[2:])%n == 0:\n        print(str(bin(i))[2:])\n        break\n",
    "lang": "Python3",
    "testCases": [
        {
            "input": "3",
            "output": "111\n"
        },
        {
            "input": "34",
            "output": "111010\n"
        },
        {
            "input": "78",
            "output": "101010\n"
        },
        {
            "input": "133",
            "output": "11101111\n"
        },
        {
            "input": "200",
            "output": "1000\n"
        }
    ]
}