{
    "title": "lambda函数",
    "desc": "### 题目描述\n\n请你写两个 lambda 函数，分别用来求出两个整数的最大值和最小值\n\n### 输入描述\n\n输入第一行为整数 a，第二行为整数 b\n\n### 输出描述\n\n输出第一行为 a 和 b 中数值大的那个，第二行输出数值小的那的\n\n### 测试样例\n\n#### 样例1: 输入-输出\n\n```\n10\n20\n```\n\n```\n20\n10\n```\n\n### 题目来源\n\nRUNOOB.COM",
    "templateCode": "",
    "sourceCode": "MAX = lambda x, y: x if x > y else y\nMIN = lambda x, y: x if x < y else y\n\na = int(input())\nb = int(input())\n\nprint(MAX(a, b))\nprint(MIN(a, b))\n",
    "lang": "Python3",
    "testCases": [
        {
            "input": "10\n20\n",
            "output": "20\n10\n"
        },
        {
            "input": "0\n-1\n",
            "output": "0\n-1\n"
        }
    ],
    "simple_desc": "创建lambda匿名函数",
    "difficulty": "2",
    "tag": "函数-lambda",
    "author": "RUNOOB"
}