{
    "title": "字符串排序",
    "desc": "### 题目描述\n\n有多个用逗号隔开的字符串，请你对这些字符串进行排序并输出\n\n### 输入描述\n\n输入为一个字符串，只包含英文字母和逗号\n\n### 输出描述\n\n按照字典序输出这些由逗号隔开的字符串，两两之间用一个逗号隔开\n\n### 测试样例\n\n#### 样例1: 输入-输出\n\n```\npython,c,java\n```\n\n```\nc,java,python\n```\n",
    "templateCode": "",
    "sourceCode": "a = input()\nl = a.split(',')\nl.sort()\nprint(','.join(l))",
    "lang": "Python3",
    "testCases": [
        {
            "input": "java,c,python\n",
            "output": "c,java,python\n"
        },
        {
            "input": "i,love,coding\n",
            "output": "coding,i,love\n"
        },
        {
            "input": "hello,world\n",
            "output": "hello,world\n"
        }
    ],
    "simple_desc": "将字符串分隔开并进行排序",
    "difficulty": "2",
    "tag": "字符串-内置函数|列表-内置函数-sort()",
    "author": "MOOCTEST"
}